mathpack/__init__.py
mathpack/directory1/__init__.py
mathpack/directory1/anyprogram1.py
mathpack/directory2/__init__.py
mathpack/directory2/anyprogram2.py
mathpack-1.0.1.dist-info/METADATA
mathpack-1.0.1.dist-info/WHEEL
mathpack-1.0.1.dist-info/top_level.txt
mathpack-1.0.1.dist-info/RECORD
